<?xml version="1.0" encoding="utf-8" ?>
<dwsync>
<file name="GEAR2.png" server="nvcmultimedia.com/jgonzalez/" local="131853970360000000" remote="131884010400000000" Dst="1" />
<file name="instagram-logo-black-transparent.png" server="nvcmultimedia.com/jgonzalez/" local="131860042300000000" remote="131884011000000000" Dst="1" />
<file name="Photo Apr 27, 12 20 26 AM.png" server="nvcmultimedia.com/jgonzalez/" local="131853970180000000" remote="131884011000000000" Dst="1" />
<file name="VansPrint.jpg" server="nvcmultimedia.com/jgonzalez/" local="131853955180000000" remote="131884011600000000" Dst="1" />
<file name="hat.jpg" server="nvcmultimedia.com/jgonzalez/" local="131882804192916221" remote="131884010400000000" Dst="1" />
<file name="IMG_5008.JPG" server="nvcmultimedia.com/jgonzalez/" local="131733899060000000" remote="131884011000000000" Dst="1" />
<file name="logo.jpg" server="nvcmultimedia.com/jgonzalez/" local="131853970600000000" remote="131884011000000000" Dst="1" />
<file name="RedRookT.png" server="nvcmultimedia.com/jgonzalez/" local="131807596712799289" remote="131884011000000000" Dst="1" />
<file name="shirts.JPG" server="nvcmultimedia.com/jgonzalez/" local="131733898160000000" remote="131884011600000000" Dst="1" />
<file name="sweet.png" server="nvcmultimedia.com/jgonzalez/" local="131458744515652424" remote="131884011600000000" Dst="1" />
<file name="sweet3.jpg" server="nvcmultimedia.com/jgonzalez/" local="131458754221437139" remote="131884011600000000" Dst="1" />
<file name="uc barbershop.jpg" server="nvcmultimedia.com/jgonzalez/" local="131282381036710045" remote="131884011600000000" Dst="1" />
</dwsync>